smxsso/__init__.py
smxsso-0.1.6.data/scripts/smxsso
smxsso-0.1.6.data/scripts/smxsso.cmd
smxsso-0.1.6.dist-info/METADATA
smxsso-0.1.6.dist-info/RECORD
smxsso-0.1.6.dist-info/WHEEL
smxsso-0.1.6.dist-info/top_level.txt
