Metadata-Version: 2.1
Name: smxsso
Version: 0.1.6
Summary: Command Line Environment for Smartronix SSO solution.
Home-page: https://github.com/changli3/smx-sso
Author: Anthony Vultaggio
Author-email: UNKNOWN
License: Apache License 2.0
Platform: UNKNOWN
Classifier: Development Status :: 5 - Production/Stable
Classifier: Intended Audience :: Developers
Classifier: Intended Audience :: System Administrators
Classifier: Natural Language :: English
Classifier: License :: OSI Approved :: Apache Software License
Classifier: Programming Language :: Python
Classifier: Programming Language :: Python :: 2
Classifier: Programming Language :: Python :: 2.6
Classifier: Programming Language :: Python :: 2.7
Classifier: Programming Language :: Python :: 3
Classifier: Programming Language :: Python :: 3.3
Classifier: Programming Language :: Python :: 3.4
Classifier: Programming Language :: Python :: 3.5
Classifier: Programming Language :: Python :: 3.6
Requires-Dist: boto
Requires-Dist: boto3
Requires-Dist: bs4
Requires-Dist: lxml
Requires-Dist: requests
Requires-Dist: awscli
Requires-Dist: argparse (>=1.1); python_version=="2.6"
